{
	"configurations" : 
	[
		{
			"directories" : 
			[
				{
					"build" : ".",
					"jsonFile" : "directory-.-Debug-d0094a50bb2071803777.json",
					"minimumCMakeVersion" : 
					{
						"string" : "3.27"
					},
					"projectIndex" : 0,
					"source" : ".",
					"targetIndexes" : 
					[
						0
					]
				}
			],
			"name" : "Debug",
			"projects" : 
			[
				{
					"directoryIndexes" : 
					[
						0
					],
					"name" : "clientsocket",
					"targetIndexes" : 
					[
						0
					]
				}
			],
			"targets" : 
			[
				{
					"directoryIndex" : 0,
					"id" : "clientsocket::@6890427a1f51a3e7e1df",
					"jsonFile" : "target-clientsocket-Debug-9e614a8e88a5ae910ae1.json",
					"name" : "clientsocket",
					"projectIndex" : 0
				}
			]
		}
	],
	"kind" : "codemodel",
	"paths" : 
	{
		"build" : "C:/Users/creid/CLionProjects/clientsocket/cmake-build-debug",
		"source" : "C:/Users/creid/CLionProjects/clientsocket"
	},
	"version" : 
	{
		"major" : 2,
		"minor" : 6
	}
}
